zbox/__init__.py
zbox-1.2.0.dist-info/DESCRIPTION.rst
zbox-1.2.0.dist-info/METADATA
zbox-1.2.0.dist-info/metadata.json
zbox-1.2.0.dist-info/RECORD
zbox-1.2.0.dist-info/top_level.txt
zbox-1.2.0.dist-info/WHEEL
