Metadata-Version: 2.0
Name: zbox
Version: 1.2.0
Summary: Get cytoolz or toolz, whatever's around
Home-page: https://github.com/jiffyclub/zbox
Author: Matt Davis
Author-email: jiffyclub@gmail.com
License: UNKNOWN
Platform: UNKNOWN
Classifier: License :: OSI Approved :: ISC License (ISCL)
Classifier: Programming Language :: Python
Classifier: Programming Language :: Python :: 2
Classifier: Programming Language :: Python :: 2.6
Classifier: Programming Language :: Python :: 2.7
Classifier: Programming Language :: Python :: 3
Classifier: Programming Language :: Python :: 3.2
Classifier: Programming Language :: Python :: 3.3
Classifier: Programming Language :: Python :: 3.4
